scidock/__init__.py
scidock/config/__init__.py
scidock/parsers/__init__.py
scidock/parsers/mathml_parser.py
scidock/parsers/query_parser.py
scidock/parsers/web_parser.py
scidock/scidock.py
scidock/search_engines/__init__.py
scidock/search_engines/arxiv_engine.py
scidock/search_engines/crossref_engine.py
scidock/search_engines/metadata.py
scidock/search_engines/scihub_engine.py
scidock/ui.py
scidock/utils.py
scidock-0.1.2.dist-info/entry_points.txt
scidock-0.1.2.dist-info/METADATA
scidock-0.1.2.dist-info/WHEEL
scidock-0.1.2.dist-info/RECORD
