Metadata-Version: 2.1
Name: scidock
Version: 0.1.2
Summary: CLI interface for finding, downloading and managing scientific articles
Home-page: https://github.com/kgleba/scidock
Keywords: research,science,free science,cli
Author: kgleba
Author-email: kgleba@yandex.ru
Requires-Python: >=3.10,<4.0
Classifier: Development Status :: 4 - Beta
Classifier: Environment :: Console
Classifier: Intended Audience :: Science/Research
Classifier: Natural Language :: English
Classifier: Natural Language :: Russian
Classifier: Operating System :: OS Independent
Classifier: Programming Language :: Python
Classifier: Programming Language :: Python :: 3
Classifier: Programming Language :: Python :: 3.10
Classifier: Programming Language :: Python :: 3.11
Classifier: Programming Language :: Python :: 3.12
Classifier: Programming Language :: Python :: 3.13
Requires-Dist: arxiv (>=2.1.2,<2.2.0)
Requires-Dist: beautifulsoup4 (>=4.12.3,<4.13.0)
Requires-Dist: click (>=8.1.7,<8.2.0)
Requires-Dist: click-params (>=0.5.0,<0.6.0)
Requires-Dist: crossrefapi (>=1.6.0,<1.7.0)
Requires-Dist: defusedxml (>=0.7.1,<0.8.0)
Requires-Dist: loguru (>=0.7.2,<0.8.0)
Requires-Dist: questionary (>=2.0.1,<2.1.0)
Requires-Dist: rapidfuzz (>=3.9.3,<3.10.0)
Requires-Dist: requests[socks] (>=2.32.3,<2.33.0)
Requires-Dist: rich (>=13.7.1,<13.8.0)
Requires-Dist: tldextract (>=5.1.2,<5.2.0)
Project-URL: Repository, https://github.com/kgleba/scidock
